my_library/__init__.py
my_library/core.py
selenium_proxy-0.1.0.dist-info/METADATA
selenium_proxy-0.1.0.dist-info/WHEEL
selenium_proxy-0.1.0.dist-info/top_level.txt
selenium_proxy-0.1.0.dist-info/RECORD
