Metadata-Version: 2.1
Name: selenium-proxy
Version: 0.1.0
Summary: Considering that there is no function that works very well natively in Selenium for using proxys with authentication in chromedriver, this is an effective way to solve this problem.
Home-page: https://github.com/kairodev/selenium-proxy
Author: Kairo Trzeciak
Author-email: trz.kairodev@gmail.com
License: MIT
Classifier: Programming Language :: Python :: 3
Classifier: License :: OSI Approved :: MIT License
Classifier: Operating System :: OS Independent
Requires-Python: >=3.6
